tabugen/__init__.py
tabugen/__main__.py
tabugen/cli.py
tabugen/lang.py
tabugen/predef.py
tabugen/registry.py
tabugen/typedef.py
tabugen/version.py
tabugen/datatran/__init__.py
tabugen/datatran/csv.py
tabugen/datatran/json.py
tabugen/generator/__init__.py
tabugen/generator/cpp/__init__.py
tabugen/generator/cpp/gen_csv_load.py
tabugen/generator/cpp/gen_struct.py
tabugen/generator/cpp/template.py
tabugen/generator/csharp/__init__.py
tabugen/generator/csharp/gen_csv_load.py
tabugen/generator/csharp/gen_struct.py
tabugen/generator/csharp/template.py
tabugen/generator/go/__init__.py
tabugen/generator/go/gen_csv_load.py
tabugen/generator/go/gen_struct.py
tabugen/generator/go/template.py
tabugen/generator/java/__init__.py
tabugen/generator/java/gen_csv_load.py
tabugen/generator/java/gen_struct.py
tabugen/generator/java/template.py
tabugen/parser/__init__.py
tabugen/parser/excel.py
tabugen/parser/xlsxhelp.py
tabugen/util/__init__.py
tabugen/util/strutil.py
tabugen/util/tableutil.py
tabugen-1.0.1.dist-info/LICENSE
tabugen-1.0.1.dist-info/METADATA
tabugen-1.0.1.dist-info/WHEEL
tabugen-1.0.1.dist-info/entry_points.txt
tabugen-1.0.1.dist-info/top_level.txt
tabugen-1.0.1.dist-info/RECORD
