Metadata-Version: 2.1
Name: tabugen
Version: 1.0.1
Summary: a spreedsheet export and code generate tool for rapid game development
Home-page: https://github.com/qki7chen/tabugen
Author: JohnnieChen
Author-email: ichenq@outlook.com
License: Apache License 2.0
Platform: UNKNOWN
Requires-Python: >=3.8
License-File: LICENSE
Requires-Dist: xlrd (>=2.0.1)
Requires-Dist: openpyxl (>=3.1.2)
